[{"__type__":"cc.SpriteFrame","content":{"name":"star_color","texture":"49KDlMnKtHPLIXYW4aUd8D","rect":[288,256,128,128],"offset":[0,0],"originalSize":[128,128],"capInsets":[0,0,0,0]}},[{"__type__":"cc.Prefab","_name":"starItem","data":{"__id__":1}},{"__type__":"cc.Node","_name":"star","_level":1,"_components":[{"__type__":"cc.Sprite","node":{"__id__":1},"_spriteFrame":{"__uuid__":"baqpF8qNtCOJp3xPq3Sozq"},"_sizeMode":0}],"_prefab":{"__type__":"cc.PrefabInfo","root":{"__id__":1},"asset":{"__uuid__":"e6queQlOVHfqX1/1YI0Kxk"},"fileId":"5fb3xZjA9LzLRiBjXgB8zH"},"_contentSize":{"__type__":"cc.Size","width":50,"height":50},"_position":{"__type__":"cc.Vec3","x":-1115,"y":-454},"_zIndex":0}]]